	public static void remove(Task task) {
		int remTaskNo = tasks.length - nofReadyTasks;
		while ((remTaskNo < tasks.length) && (tasks[remTaskNo] != task)) remTaskNo++;
		if (remTaskNo < tasks.length) {
			tasks[remTaskNo] = tasks[tasks.length - nofReadyTasks]; 
			nofReadyTasks--;
		} else
			removePeriodicTask(task);
		task.installed = false;
	}

	"public static void remove(Lch/ntb/inf/deep/runtime/mpc555/Task;)"
	//nofStackSlots=5, nofLocalSlots=2, codeLen=79 
	{
		  0 getstatic ch/ntb/inf/deep/runtime/mpc555/Task.tasks: Lch/ntb/inf/deep/runtime/mpc555/Task[];
		  3 arraylength
		  4 getstatic ch/ntb/inf/deep/runtime/mpc555/Task.nofReadyTasks: short
		  7 isub
		  8 istore_1 [remTaskNo]
		  9 goto 15
		 12 iinc remTaskNo, 1
		 15 iload_1 [remTaskNo]
		 16 getstatic ch/ntb/inf/deep/runtime/mpc555/Task.tasks: Lch/ntb/inf/deep/runtime/mpc555/Task[];
		 19 arraylength
		 20 if_icmpge 32
		 23 getstatic ch/ntb/inf/deep/runtime/mpc555/Task.tasks: Lch/ntb/inf/deep/runtime/mpc555/Task[];
		 26 iload_1 [remTaskNo]
		 27 aaload
		 28 aload_0 [task]
		 29 if_acmpne 12
		 32 iload_1 [remTaskNo]
		 33 getstatic ch/ntb/inf/deep/runtime/mpc555/Task.tasks: Lch/ntb/inf/deep/runtime/mpc555/Task[];
		 36 arraylength
		 37 if_icmpge 69
		 40 getstatic ch/ntb/inf/deep/runtime/mpc555/Task.tasks: Lch/ntb/inf/deep/runtime/mpc555/Task[];
		 43 iload_1 [remTaskNo]
		 44 getstatic ch/ntb/inf/deep/runtime/mpc555/Task.tasks: Lch/ntb/inf/deep/runtime/mpc555/Task[];
		 47 getstatic ch/ntb/inf/deep/runtime/mpc555/Task.tasks: Lch/ntb/inf/deep/runtime/mpc555/Task[];
		 50 arraylength
		 51 getstatic ch/ntb/inf/deep/runtime/mpc555/Task.nofReadyTasks: short
		 54 isub
		 55 aaload
		 56 aastore
		 57 getstatic ch/ntb/inf/deep/runtime/mpc555/Task.nofReadyTasks: short
		 60 iconst_1
		 61 isub
		 62 i2s
		 63 putstatic ch/ntb/inf/deep/runtime/mpc555/Task.nofReadyTasks: short
		 66 goto 73
		 69 aload_0 [task]
		 70 invokestatic ch/ntb/inf/deep/runtime/mpc555/Task.removePeriodicTask(Lch/ntb/inf/deep/runtime/mpc555/Task;): void
		 73 aload_0 [task]
		 74 iconst_0
		 75 putfield ch/ntb/inf/deep/runtime/mpc555/Task.installed: boolean
		 78 return
